novautils/__init__.py
novautils-0.0.2.dist-info/LICENSE
novautils-0.0.2.dist-info/METADATA
novautils-0.0.2.dist-info/WHEEL
novautils-0.0.2.dist-info/top_level.txt
novautils-0.0.2.dist-info/RECORD
