Metadata-Version: 2.1
Name: novautils
Version: 0.0.2
Summary: Custom utility package
Home-page: https://github.com/novasush/novautils
Author: Sushrut Ashtikar
Author-email: sushrut@nsemble.ai
License: UNKNOWN
Platform: UNKNOWN
Classifier: Programming Language :: Python :: 3
Classifier: License :: OSI Approved :: MIT License
Classifier: Operating System :: OS Independent
Requires-Python: >=3.6
